setup.py
brynq_sdk_sharepoint/__init__.py
brynq_sdk_sharepoint/sharepoint.py
brynq_sdk_sharepoint.egg-info/PKG-INFO
brynq_sdk_sharepoint.egg-info/SOURCES.txt
brynq_sdk_sharepoint.egg-info/dependency_links.txt
brynq_sdk_sharepoint.egg-info/not-zip-safe
brynq_sdk_sharepoint.egg-info/requires.txt
brynq_sdk_sharepoint.egg-info/top_level.txt