Metadata-Version: 1.0
Name: brynq-sdk-sharepoint
Version: 2.0.2
Summary: Sharepoint wrapper from BrynQ
Home-page: UNKNOWN
Author: BrynQ
Author-email: support@brynq.com
License: BrynQ License
Platform: UNKNOWN
